MANIFEST.in
README.md
setup.cfg
setup.py
flappy_bird_ai/__init__.py
flappy_bird_ai/flappy.py
flappy_bird_ai.egg-info/PKG-INFO
flappy_bird_ai.egg-info/SOURCES.txt
flappy_bird_ai.egg-info/dependency_links.txt
flappy_bird_ai.egg-info/not-zip-safe
flappy_bird_ai.egg-info/requires.txt
flappy_bird_ai.egg-info/top_level.txt
flappy_bird_ai/assets/audio/die.ogg
flappy_bird_ai/assets/audio/die.wav
flappy_bird_ai/assets/audio/hit.ogg
flappy_bird_ai/assets/audio/hit.wav
flappy_bird_ai/assets/audio/point.ogg
flappy_bird_ai/assets/audio/point.wav
flappy_bird_ai/assets/audio/swoosh.ogg
flappy_bird_ai/assets/audio/swoosh.wav
flappy_bird_ai/assets/audio/wing.ogg
flappy_bird_ai/assets/audio/wing.wav
flappy_bird_ai/assets/sprites/0.png
flappy_bird_ai/assets/sprites/1.png
flappy_bird_ai/assets/sprites/2.png
flappy_bird_ai/assets/sprites/3.png
flappy_bird_ai/assets/sprites/4.png
flappy_bird_ai/assets/sprites/5.png
flappy_bird_ai/assets/sprites/6.png
flappy_bird_ai/assets/sprites/7.png
flappy_bird_ai/assets/sprites/8.png
flappy_bird_ai/assets/sprites/9.png
flappy_bird_ai/assets/sprites/background-day.png
flappy_bird_ai/assets/sprites/background-night.png
flappy_bird_ai/assets/sprites/base.png
flappy_bird_ai/assets/sprites/bluebird-downflap.png
flappy_bird_ai/assets/sprites/bluebird-midflap.png
flappy_bird_ai/assets/sprites/bluebird-upflap.png
flappy_bird_ai/assets/sprites/gameover.png
flappy_bird_ai/assets/sprites/message.png
flappy_bird_ai/assets/sprites/pipe-green.png
flappy_bird_ai/assets/sprites/pipe-red.png
flappy_bird_ai/assets/sprites/redbird-downflap.png
flappy_bird_ai/assets/sprites/redbird-midflap.png
flappy_bird_ai/assets/sprites/redbird-upflap.png
flappy_bird_ai/assets/sprites/yellowbird-downflap.png
flappy_bird_ai/assets/sprites/yellowbird-midflap.png
flappy_bird_ai/assets/sprites/yellowbird-upflap.png