Metadata-Version: 1.0
Name: flappy-bird-ai
Version: 0.1
Summary: A version of Flappy for illustrating some AI methods.
Home-page: UNKNOWN
Author: UNKNOWN
Author-email: UNKNOWN
License: BSD 3-Clause License
Platform: UNKNOWN
